alchemyapi_python-1.2.1.dist-info/metadata.json
alchemyapi_python-1.2.1.dist-info/WHEEL
alchemyapi_python-1.2.1.dist-info/top_level.txt
alchemyapi_python-1.2.1.dist-info/DESCRIPTION.rst
alchemyapi_python-1.2.1.dist-info/METADATA
alchemyapi_python-1.2.1.dist-info/RECORD
alchemyapi_python-1.2.1.dist-info/pbr.json
alchemyapi/__init__.py
alchemyapi/alchemyapi.py
