Metadata-Version: 2.0
Name: alchemyapi-python
Version: 1.2.1
Summary: Enhanced version of AlchemyAPI Python SDK
Home-page: https://github.com/AlchemyAPI/alchemyapi_python
Author: AlchemyAPI
Author-email: support@alchemyapi.com
License: Apache
Platform: UNKNOWN
Classifier: Environment :: Web Environment
Classifier: Intended Audience :: Developers
Classifier: Operating System :: OS Independent
Classifier: Programming Language :: Python
Classifier: Programming Language :: Python :: 2.7
Classifier: Programming Language :: Python :: 3.4
Classifier: Topic :: Internet :: WWW/HTTP :: Dynamic Content
Classifier: Topic :: Software Development :: Libraries :: Python Modules
Requires-Dist: requests
